privatechatbot/__init__.py
privatechatbot/core.py
privatechatbot/testing.py
privatechatbot-0.2.dist-info/METADATA
privatechatbot-0.2.dist-info/WHEEL
privatechatbot-0.2.dist-info/top_level.txt
privatechatbot-0.2.dist-info/RECORD
