Metadata-Version: 2.1
Name: privatechatbot
Version: 0.2
Summary: An SDK for interacting with the Private Chatbot API
Home-page: https://github.com/nv78/Anote
Author: Natan Vidra
Author-email: nvidra@anote.ai
License: MIT
Platform: UNKNOWN
Requires-Dist: requests
